src/__init__.py
src/cli.py
src/generator.py
src/models/__init__.py
src/models/schemas.py
src/templates/__init__.py
src/templates/prompts.py
iva_generator-0.1.2.dist-info/METADATA
iva_generator-0.1.2.dist-info/WHEEL
iva_generator-0.1.2.dist-info/entry_points.txt
iva_generator-0.1.2.dist-info/top_level.txt
iva_generator-0.1.2.dist-info/RECORD
