Metadata-Version: 2.4
Name: iva-generator
Version: 0.1.2
Summary: AI Code Assistant
Home-page: https://github.com/ItzCyzmiX/Iva
Author: ItzCyzmiX
Author-email: itzmedigamingx@gmail.com
Project-URL: Bug Tracker, https://github.com/ItzCyzmiX/Iva/issues
Project-URL: Documentation, https://github.com/ItzCyzmiX/Iva#readme
Project-URL: Source Code, https://github.com/ItzCyzmiX/Iva
Keywords: ai,code generator,assistant,development
Classifier: Development Status :: 3 - Alpha
Classifier: Intended Audience :: Developers
Classifier: Programming Language :: Python :: 3
Classifier: Programming Language :: Python :: 3.8
Classifier: Programming Language :: Python :: 3.9
Classifier: Programming Language :: Python :: 3.10
Classifier: Programming Language :: Python :: 3.11
Classifier: License :: OSI Approved :: MIT License
Classifier: Operating System :: OS Independent
Classifier: Topic :: Software Development :: Libraries :: Python Modules
Requires-Python: >=3.8
Requires-Dist: langchain
Requires-Dist: langchain-community
Requires-Dist: langchain-groq
Requires-Dist: python-dotenv
Requires-Dist: pydantic
Requires-Dist: rich
Dynamic: author
Dynamic: author-email
Dynamic: classifier
Dynamic: description
Dynamic: description-content-type
Dynamic: home-page
Dynamic: keywords
Dynamic: project-url
Dynamic: requires-dist
Dynamic: requires-python
Dynamic: summary
